image_processing_danilo/__init__.py
image_processing_danilo/processing/__init__.py
image_processing_danilo/processing/combination.py
image_processing_danilo/processing/transformation.py
image_processing_danilo/utils/__init__.py
image_processing_danilo/utils/io.py
image_processing_danilo/utils/plot.py
image_processing_danilo-0.0.1.dist-info/METADATA
image_processing_danilo-0.0.1.dist-info/WHEEL
image_processing_danilo-0.0.1.dist-info/top_level.txt
image_processing_danilo-0.0.1.dist-info/RECORD
