Metadata-Version: 2.4
Name: image_processing_danilo
Version: 0.0.1
Summary: image Processing Package using Skimage
Author: Danilo
Author-email: danilo.r.oliveira1@gmail.com
Requires-Python: >=3.8
Requires-Dist: matplotlib==3.10.3
Requires-Dist: numpy
Requires-Dist: scikit-image==0.25.2
Dynamic: author
Dynamic: author-email
Dynamic: description
Dynamic: description-content-type
Dynamic: requires-dist
Dynamic: requires-python
Dynamic: summary
